mist_stitching/__init__.py
mist_stitching/assemble.py
mist_stitching/build_and_publish.py
mist_stitching/img_grid.py
mist_stitching/img_tile.py
mist_stitching/main.py
mist_stitching/main_csv.py
mist_stitching/mle_estimator.py
mist_stitching/pciam.py
mist_stitching/stage_model.py
mist_stitching/translation_refinement.py
mist_stitching/utils.py
mist_stitching-1.0.0.dist-info/METADATA
mist_stitching-1.0.0.dist-info/WHEEL
mist_stitching-1.0.0.dist-info/licenses/LICENSE
mist_stitching-1.0.0.dist-info/RECORD
