Metadata-Version: 2.4
Name: mist_stitching
Version: 1.0.0
Summary: MIST: Microscopy Image Stitching Tool
Project-URL: Homepage, https://github.com/usnistgov/MIST
Author-email: Michael Majurski <michael.majurski@nist.gov>
License-File: LICENSE
Requires-Python: >=3.10
Requires-Dist: numpy>=2.3.2
Requires-Dist: pandas>=2.3.1
Requires-Dist: scikit-image>=0.25.2
